turbinia/__init__.py
turbinia/api/__init__.py
turbinia/api/api_server.py
turbinia/api/api_server_test.py
turbinia/api/cli/.turbinia_api_config.json
turbinia/api/cli/LICENSE
turbinia/api/cli/README.rst
turbinia/api/cli/poetry.lock
turbinia/api/cli/pyproject.toml
turbinia/api/cli/requirements.txt
turbinia/api/cli/turbinia_client/__init__.py
turbinia/api/cli/turbinia_client/core/__init__.py
turbinia/api/cli/turbinia_client/core/commands.py
turbinia/api/cli/turbinia_client/core/groups.py
turbinia/api/cli/turbinia_client/factory/__init__.py
turbinia/api/cli/turbinia_client/factory/factory.py
turbinia/api/cli/turbinia_client/helpers/__init__.py
turbinia/api/cli/turbinia_client/helpers/auth_helper.py
turbinia/api/cli/turbinia_client/helpers/click_helper.py
turbinia/api/cli/turbinia_client/helpers/formatter.py
turbinia/api/cli/turbinia_client/helpers/formatter_test.py
turbinia/api/cli/turbinia_client/turbiniacli.py
turbinia/api/cli/turbinia_client/turbiniacli_test.py
turbinia/api/cli/turbinia_client/turbiniacli_tool.py
turbinia/api/client/.github/workflows/python.yml
turbinia/api/client/.gitignore
turbinia/api/client/.gitlab-ci.yml
turbinia/api/client/.openapi-generator-ignore
turbinia/api/client/.travis.yml
turbinia/api/client/LICENSE
turbinia/api/client/README.md
turbinia/api/client/docs/BaseRequestOptions.md
turbinia/api/client/docs/CompleteTurbiniaStats.md
turbinia/api/client/docs/HTTPValidationError.md
turbinia/api/client/docs/LocationInner.md
turbinia/api/client/docs/Request.md
turbinia/api/client/docs/TurbiniaConfigurationApi.md
turbinia/api/client/docs/TurbiniaEvidenceApi.md
turbinia/api/client/docs/TurbiniaJobsApi.md
turbinia/api/client/docs/TurbiniaLogsApi.md
turbinia/api/client/docs/TurbiniaRequestResultsApi.md
turbinia/api/client/docs/TurbiniaRequestsApi.md
turbinia/api/client/docs/TurbiniaTasksApi.md
turbinia/api/client/docs/ValidationError.md
turbinia/api/client/git_push.sh
turbinia/api/client/poetry.lock
turbinia/api/client/pyproject.toml
turbinia-20240820.dist-info/AUTHORS
turbinia-20240820.dist-info/LICENSE
turbinia-20240820.dist-info/METADATA
turbinia-20240820.dist-info/WHEEL
turbinia-20240820.dist-info/entry_points.txt
turbinia-20240820.dist-info/RECORD
