Metadata-Version: 2.1
Name: turbinia
Version: 20240820
Summary: Automation and Scaling of Digital Forensics Tools
Home-page: https://github.com/google/turbinia
License: Apache-2.0
Author: Turbinia Developers
Author-email: turbinia-dev@googlegroups.com
Maintainer: Turbinia Developers
Maintainer-email: turbinia-dev@googlegroups.com
Requires-Python: >=3.10,<4.0
Classifier: License :: OSI Approved :: Apache Software License
Classifier: Programming Language :: Python :: 3
Classifier: Programming Language :: Python :: 3.10
Classifier: Programming Language :: Python :: 3.11
Classifier: Programming Language :: Python :: 3.12
Provides-Extra: worker
Requires-Dist: acstore (==20240128)
Requires-Dist: backoff (>=2.2.1)
Requires-Dist: celery (>=5.2.2,<6.0.0)
Requires-Dist: debugpy (>=1.8.0,<2.0.0)
Requires-Dist: dfDewey (>=20231016,<20231017) ; extra == "worker"
Requires-Dist: dfimagetools (>=20240301,<20240302) ; extra == "worker"
Requires-Dist: docker (>=6.1.3,<7.0.0)
Requires-Dist: fastapi[all] (>=0.75.0,<0.99.0)
Requires-Dist: filelock
Requires-Dist: google-api-core (<3.0.0)
Requires-Dist: google-generativeai (>=0.3.2)
Requires-Dist: jurigged (>=0.5.7,<0.6.0)
Requires-Dist: libcloudforensics (>=20240325,<20240326)
Requires-Dist: opensearch-py (==2.4.2)
Requires-Dist: pandas (>=2.1.0,<3.0.0)
Requires-Dist: plaso (==20240308) ; extra == "worker"
Requires-Dist: prometheus_client (>=0.17.1,<0.18.0)
Requires-Dist: protobuf (>=3.19.0)
Requires-Dist: pydantic (>=1.10.5,<2.0.0)
Requires-Dist: pyglove (>=0.4.4)
Requires-Dist: pyhindsight (>=20230327.0,<20230328.0) ; extra == "worker"
Requires-Dist: ratelimit (>=2.2.1)
Requires-Dist: redis (>=4.4.4,<5.0.0)
Requires-Dist: urllib3 (>=1.25.4,<1.27) ; python_version < "3.10"
Requires-Dist: urllib3 (>=1.25.4,<2.1) ; python_version >= "3.10"
Project-URL: Documentation, https://turbinia.readthedocs.io/en/latest/
Project-URL: Repository, https://github.com/google/turbinia
